{
    "exec_id": 74,
    "dot_name": "alu4_k6",
    "dot_path": "/home/jeronimo/GIT/PeR/benchmarks/fpga/bench_test/alu4_k6.dot",
    "placer": "yott",
    "edges_algorithm": "ZIG_ZAG",
    "total_cost": 55136.9,
    "histogram": {
        "1": 106,
        "2": 49,
        "3": 70,
        "4": 58,
        "5": 79,
        "6": 74,
        "7": 79,
        "8": 84,
        "9": 94,
        "10": 88,
        "11": 88,
        "12": 97,
        "13": 107,
        "14": 102,
        "15": 97,
        "16": 104,
        "17": 100,
        "18": 105,
        "19": 88,
        "20": 90,
        "21": 106,
        "22": 103,
        "23": 93,
        "24": 95,
        "25": 86,
        "26": 90,
        "27": 94,
        "28": 79,
        "29": 76,
        "30": 68,
        "31": 68,
        "32": 56,
        "33": 40,
        "34": 31,
        "35": 37,
        "36": 29,
        "37": 31,
        "38": 35,
        "39": 17,
        "40": 15,
        "41": 15,
        "42": 13,
        "43": 8,
        "44": 8,
        "45": 8,
        "46": 6,
        "47": 8,
        "48": 5,
        "49": 6,
        "50": 4,
        "51": 2,
        "52": 1,
        "53": 3
    },
    "longest_path_cost": 112.9,
    "placement": [
        null,
        null,
        521,
        1,
        714,
        679,
        758,
        502,
        775,
        132,
        347,
        432,
        164,
        577,
        7,
        505,
        510,
        12,
        61,
        8,
        56,
        310,
        837,
        412,
        671,
        516,
        23,
        726,
        631,
        null,
        346,
        716,
        320,
        676,
        308,
        50,
        231,
        709,
        606,
        686,
        307,
        710,
        582,
        232,
        348,
        181,
        175,
        27,
        169,
        239,
        244,
        704,
        13,
        827,
        830,
        120,
        819,
        727,
        382,
        735,
        null,
        457,
        770,
        155,
        314,
        798,
        567,
        566,
        675,
        419,
        283,
        447,
        532,
        599,
        374,
        397,
        19,
        9,
        66,
        396,
        399,
        41,
        0,
        268,
        352,
        20,
        254,
        834,
        366,
        435,
        null,
        159,
        84,
        213,
        424,
        556,
        75,
        126,
        578,
        34,
        779,
        37,
        31,
        537,
        774,
        563,
        501,
        17,
        764,
        47,
        189,
        49,
        729,
        125,
        812,
        828,
        230,
        271,
        270,
        6,
        null,
        256,
        485,
        650,
        565,
        754,
        196,
        747,
        468,
        621,
        203,
        813,
        486,
        831,
        672,
        788,
        756,
        311,
        209,
        667,
        433,
        507,
        99,
        64,
        713,
        154,
        234,
        572,
        767,
        820,
        426,
        274,
        655,
        816,
        602,
        240,
        133,
        186,
        45,
        187,
        263,
        105,
        212,
        689,
        677,
        420,
        421,
        85,
        609,
        833,
        109,
        385,
        63,
        437,
        608,
        738,
        335,
        191,
        160,
        59,
        802,
        488,
        206,
        87,
        205,
        111,
        90,
        174,
        291,
        180,
        568,
        11,
        112,
        416,
        694,
        809,
        600,
        628,
        520,
        783,
        67,
        594,
        839,
        398,
        344,
        789,
        177,
        389,
        632,
        65,
        699,
        131,
        836,
        649,
        728,
        228,
        294,
        55,
        625,
        804,
        313,
        496,
        674,
        293,
        630,
        552,
        487,
        702,
        429,
        768,
        737,
        741,
        706,
        183,
        717,
        130,
        158,
        387,
        815,
        842,
        440,
        530,
        351,
        408,
        454,
        748,
        805,
        342,
        793,
        558,
        817,
        626,
        647,
        541,
        224,
        290,
        548,
        692,
        524,
        26,
        62,
        657,
        68,
        81,
        46,
        841,
        773,
        21,
        309,
        583,
        648,
        637,
        197,
        184,
        190,
        494,
        53,
        473,
        330,
        618,
        535,
        10,
        300,
        250,
        3,
        182,
        825,
        48,
        703,
        517,
        698,
        353,
        170,
        562,
        407,
        504,
        161,
        533,
        306,
        469,
        542,
        707,
        808,
        635,
        405,
        629,
        417,
        273,
        792,
        724,
        157,
        682,
        332,
        127,
        390,
        573,
        684,
        733,
        587,
        445,
        470,
        478,
        185,
        284,
        406,
        666,
        116,
        148,
        267,
        14,
        560,
        443,
        693,
        388,
        462,
        646,
        610,
        690,
        777,
        51,
        660,
        315,
        110,
        144,
        222,
        115,
        665,
        732,
        799,
        771,
        829,
        623,
        518,
        71,
        176,
        173,
        262,
        482,
        265,
        83,
        778,
        264,
        377,
        475,
        604,
        784,
        245,
        835,
        333,
        762,
        329,
        269,
        822,
        356,
        806,
        725,
        821,
        253,
        751,
        193,
        369,
        580,
        434,
        503,
        350,
        162,
        118,
        252,
        376,
        16,
        171,
        384,
        194,
        481,
        569,
        681,
        640,
        545,
        30,
        25,
        322,
        790,
        415,
        491,
        456,
        172,
        605,
        795,
        91,
        476,
        403,
        422,
        202,
        449,
        147,
        316,
        22,
        404,
        251,
        58,
        255,
        761,
        142,
        321,
        742,
        797,
        477,
        324,
        575,
        589,
        668,
        464,
        786,
        781,
        497,
        508,
        72,
        79,
        570,
        88,
        581,
        210,
        442,
        188,
        355,
        327,
        423,
        129,
        498,
        32,
        543,
        780,
        590,
        317,
        515,
        550,
        586,
        760,
        769,
        40,
        241,
        286,
        499,
        765,
        826,
        743,
        354,
        622,
        178,
        358,
        363,
        673,
        428,
        561,
        452,
        455,
        77,
        52,
        373,
        60,
        98,
        null,
        603,
        101,
        439,
        472,
        394,
        167,
        103,
        33,
        460,
        592,
        331,
        114,
        697,
        381,
        221,
        149,
        598,
        718,
        117,
        616,
        2,
        500,
        362,
        375,
        474,
        490,
        379,
        141,
        null,
        null,
        165,
        289,
        708,
        280,
        493,
        336,
        431,
        529,
        810,
        380,
        639,
        615,
        752,
        800,
        719,
        721,
        840,
        248,
        78,
        208,
        325,
        409,
        528,
        236,
        370,
        411,
        145,
        372,
        null,
        null,
        null,
        108,
        414,
        526,
        5,
        93,
        739,
        304,
        319,
        345,
        339,
        367,
        207,
        659,
        772,
        757,
        128,
        451,
        323,
        438,
        261,
        425,
        662,
        138,
        226,
        664,
        400,
        198,
        446,
        641,
        null,
        null,
        null,
        547,
        670,
        695,
        4,
        305,
        749,
        448,
        326,
        219,
        337,
        576,
        233,
        661,
        430,
        838,
        395,
        100,
        15,
        220,
        763,
        557,
        302,
        734,
        266,
        163,
        341,
        696,
        null,
        null,
        null,
        null,
        343,
        364,
        722,
        361,
        723,
        166,
        43,
        436,
        564,
        349,
        73,
        519,
        214,
        402,
        794,
        766,
        179,
        229,
        200,
        634,
        736,
        70,
        242,
        461,
        642,
        687,
        441,
        null,
        null,
        null,
        null,
        645,
        471,
        730,
        513,
        613,
        554,
        97,
        168,
        227,
        340,
        296,
        539,
        124,
        151,
        281,
        217,
        579,
        458,
        753,
        218,
        484,
        152,
        638,
        null,
        318,
        39,
        782,
        null,
        null,
        null,
        495,
        489,
        549,
        776,
        611,
        506,
        192,
        204,
        691,
        601,
        627,
        298,
        450,
        36,
        123,
        483,
        619,
        546,
        427,
        759,
        95,
        139,
        410,
        null,
        678,
        42,
        653,
        38,
        null,
        null,
        null,
        null,
        106,
        651,
        24,
        512,
        211,
        137,
        479,
        276,
        299,
        744,
        720,
        89,
        371,
        480,
        466,
        29,
        143,
        755,
        571,
        153,
        740,
        null,
        811,
        76,
        383,
        44,
        359,
        null,
        null,
        null,
        null,
        544,
        523,
        700,
        146,
        652,
        28,
        392,
        712,
        223,
        617,
        80,
        818,
        463,
        525,
        285,
        654,
        531,
        225,
        467,
        574,
        35,
        680,
        624,
        107,
        360,
        334,
        378,
        588,
        null,
        null,
        null,
        731,
        591,
        584,
        249,
        551,
        612,
        715,
        119,
        297,
        122,
        393,
        459,
        656,
        633,
        237,
        279,
        292,
        328,
        803,
        785,
        787,
        86,
        553,
        257,
        136,
        511,
        82,
        null,
        null,
        null,
        102,
        796,
        791,
        663,
        368,
        807,
        669,
        277,
        295,
        555,
        201,
        597,
        401,
        247,
        711,
        121,
        357,
        74,
        272,
        null,
        258,
        156,
        216,
        135,
        509,
        540,
        593,
        195,
        null,
        null,
        643,
        338,
        282,
        701,
        814,
        683,
        636,
        94,
        238,
        658,
        746,
        386,
        57,
        54,
        96,
        620,
        303,
        18,
        492,
        null,
        246,
        199,
        301,
        536,
        824,
        514,
        614,
        391,
        453,
        null,
        null,
        null,
        444,
        522,
        140,
        688,
        113,
        644,
        465,
        534,
        134,
        596,
        607,
        235,
        278,
        538,
        260,
        750,
        823,
        null,
        null,
        null,
        215,
        104,
        null,
        null,
        585,
        null,
        288,
        275,
        92,
        418,
        801,
        365,
        527,
        259,
        745,
        832,
        413,
        312,
        243,
        595,
        287,
        150,
        685,
        559,
        705,
        69,
        null
    ],
    "n2c": [
        82,
        3,
        502,
        284,
        578,
        546,
        119,
        14,
        19,
        77,
        281,
        191,
        17,
        52,
        329,
        592,
        389,
        107,
        838,
        76,
        85,
        267,
        416,
        26,
        701,
        399,
        259,
        47,
        735,
        714,
        398,
        102,
        449,
        489,
        99,
        750,
        680,
        101,
        694,
        662,
        459,
        81,
        692,
        612,
        724,
        158,
        264,
        109,
        287,
        111,
        35,
        339,
        477,
        276,
        834,
        217,
        20,
        833,
        419,
        179,
        479,
        18,
        260,
        172,
        143,
        209,
        78,
        200,
        262,
        898,
        627,
        353,
        436,
        616,
        808,
        96,
        722,
        476,
        530,
        437,
        740,
        263,
        787,
        359,
        92,
        167,
        782,
        183,
        439,
        710,
        186,
        408,
        881,
        547,
        828,
        687,
        835,
        643,
        480,
        142,
        591,
        483,
        791,
        488,
        874,
        161,
        699,
        753,
        543,
        170,
        342,
        185,
        192,
        857,
        493,
        345,
        326,
        500,
        386,
        768,
        55,
        806,
        770,
        681,
        649,
        113,
        97,
        313,
        558,
        447,
        235,
        211,
        9,
        156,
        861,
        814,
        785,
        704,
        565,
        688,
        855,
        509,
        422,
        715,
        343,
        538,
        733,
        414,
        327,
        497,
        894,
        650,
        658,
        718,
        145,
        63,
        812,
        310,
        236,
        91,
        178,
        296,
        385,
        599,
        12,
        512,
        611,
        487,
        644,
        48,
        292,
        390,
        405,
        355,
        187,
        46,
        354,
        206,
        468,
        622,
        189,
        45,
        285,
        233,
        273,
        322,
        157,
        159,
        443,
        110,
        274,
        177,
        673,
        379,
        392,
        818,
        126,
        272,
        569,
        842,
        624,
        801,
        412,
        130,
        674,
        184,
        182,
        554,
        531,
        138,
        441,
        703,
        162,
        93,
        618,
        873,
        813,
        652,
        656,
        583,
        593,
        496,
        344,
        738,
        254,
        747,
        566,
        645,
        215,
        623,
        116,
        36,
        43,
        586,
        146,
        864,
        535,
        775,
        829,
        49,
        155,
        460,
        628,
        891,
        50,
        366,
        841,
        804,
        529,
        764,
        283,
        418,
        387,
        377,
        86,
        420,
        121,
        784,
        811,
        886,
        867,
        562,
        356,
        160,
        361,
        358,
        598,
        328,
        83,
        371,
        118,
        117,
        809,
        307,
        151,
        880,
        706,
        798,
        865,
        776,
        515,
        651,
        823,
        70,
        323,
        744,
        461,
        893,
        879,
        513,
        255,
        188,
        777,
        223,
        216,
        799,
        647,
        769,
        678,
        707,
        282,
        843,
        596,
        837,
        549,
        579,
        298,
        40,
        34,
        268,
        21,
        137,
        890,
        220,
        64,
        341,
        415,
        453,
        661,
        550,
        32,
        423,
        400,
        560,
        427,
        532,
        582,
        445,
        778,
        370,
        278,
        492,
        312,
        368,
        755,
        176,
        517,
        584,
        822,
        552,
        646,
        600,
        247,
        606,
        204,
        551,
        30,
        10,
        44,
        615,
        384,
        242,
        84,
        291,
        466,
        444,
        373,
        807,
        469,
        725,
        754,
        609,
        504,
        470,
        607,
        884,
        88,
        553,
        795,
        380,
        536,
        711,
        539,
        478,
        74,
        505,
        388,
        362,
        756,
        508,
        521,
        495,
        58,
        723,
        391,
        171,
        832,
        237,
        333,
        207,
        314,
        848,
        736,
        771,
        486,
        590,
        79,
        75,
        203,
        80,
        568,
        803,
        619,
        410,
        417,
        304,
        324,
        294,
        243,
        533,
        689,
        537,
        23,
        889,
        544,
        402,
        193,
        306,
        882,
        69,
        165,
        166,
        411,
        446,
        94,
        563,
        150,
        685,
        472,
        228,
        588,
        518,
        11,
        140,
        382,
        89,
        613,
        173,
        561,
        484,
        240,
        632,
        442,
        331,
        853,
        319,
        570,
        71,
        581,
        413,
        679,
        559,
        474,
        849,
        244,
        475,
        404,
        61,
        654,
        772,
        490,
        629,
        334,
        742,
        431,
        859,
        713,
        748,
        128,
        299,
        320,
        638,
        485,
        277,
        506,
        363,
        409,
        426,
        321,
        705,
        712,
        393,
        357,
        682,
        657,
        122,
        132,
        226,
        181,
        668,
        507,
        403,
        839,
        516,
        275,
        667,
        221,
        434,
        448,
        462,
        503,
        106,
        7,
        383,
        295,
        15,
        672,
        141,
        435,
        815,
        16,
        786,
        702,
        640,
        846,
        454,
        25,
        289,
        352,
        617,
        198,
        2,
        854,
        731,
        258,
        743,
        545,
        885,
        534,
        519,
        241,
        746,
        72,
        297,
        860,
        280,
        844,
        103,
        866,
        648,
        816,
        253,
        300,
        450,
        730,
        397,
        684,
        575,
        256,
        669,
        455,
        765,
        225,
        783,
        642,
        800,
        95,
        595,
        249,
        896,
        330,
        473,
        293,
        105,
        614,
        124,
        67,
        66,
        190,
        394,
        438,
        717,
        147,
        315,
        749,
        428,
        585,
        13,
        98,
        653,
        381,
        440,
        42,
        269,
        763,
        877,
        456,
        318,
        757,
        429,
        452,
        762,
        491,
        817,
        201,
        892,
        862,
        802,
        498,
        73,
        196,
        676,
        154,
        482,
        364,
        406,
        38,
        863,
        174,
        168,
        336,
        671,
        766,
        641,
        847,
        523,
        501,
        739,
        279,
        683,
        836,
        129,
        467,
        351,
        752,
        218,
        251,
        677,
        197,
        305,
        224,
        28,
        208,
        774,
        625,
        303,
        827,
        271,
        659,
        522,
        396,
        571,
        630,
        821,
        858,
        637,
        335,
        252,
        270,
        213,
        123,
        700,
        734,
        693,
        745,
        152,
        773,
        261,
        830,
        555,
        340,
        587,
        564,
        794,
        567,
        346,
        325,
        139,
        430,
        797,
        576,
        24,
        134,
        471,
        222,
        68,
        33,
        164,
        691,
        5,
        751,
        395,
        311,
        826,
        316,
        895,
        39,
        631,
        856,
        163,
        337,
        675,
        257,
        332,
        194,
        577,
        601,
        494,
        290,
        210,
        732,
        824,
        227,
        288,
        51,
        897,
        232,
        301,
        514,
        37,
        41,
        805,
        737,
        144,
        4,
        767,
        31,
        234,
        499,
        526,
        709,
        527,
        608,
        610,
        309,
        375,
        27,
        57,
        214,
        112,
        639,
        761,
        347,
        317,
        597,
        59,
        626,
        230,
        175,
        548,
        719,
        231,
        424,
        465,
        708,
        887,
        831,
        127,
        245,
        580,
        868,
        378,
        524,
        655,
        125,
        716,
        136,
        557,
        6,
        686,
        457,
        421,
        369,
        594,
        108,
        463,
        621,
        148,
        229,
        458,
        62,
        349,
        556,
        266,
        104,
        8,
        670,
        338,
        360,
        100,
        451,
        433,
        663,
        199,
        365,
        780,
        432,
        781,
        135,
        205,
        401,
        793,
        308,
        248,
        620,
        407,
        792,
        425,
        65,
        348,
        525,
        883,
        180,
        779,
        219,
        246,
        374,
        796,
        302,
        195,
        520,
        721,
        114,
        131,
        825,
        238,
        153,
        250,
        741,
        56,
        149,
        376,
        372,
        869,
        845,
        286,
        464,
        53,
        115,
        350,
        54,
        133,
        888,
        169,
        87,
        367,
        212,
        22,
        589,
        202,
        528,
        265,
        239
    ]
}