{
    "exec_id": 15,
    "dot_name": "apex4_k6",
    "dot_path": "/home/jeronimo/GIT/PeR/benchmarks/fpga/bench_test/apex4_k6.dot",
    "placer": "yoto",
    "tries": 6775,
    "swaps": 777,
    "edges_algorithm": "DEPTH_FIRST_WITH_PRIORITY",
    "total_cost": 43863.1,
    "histogram": {
        "1": 114,
        "2": 57,
        "3": 56,
        "4": 68,
        "5": 75,
        "6": 79,
        "7": 97,
        "8": 107,
        "9": 77,
        "10": 84,
        "11": 118,
        "12": 103,
        "13": 116,
        "14": 107,
        "15": 105,
        "16": 106,
        "17": 118,
        "18": 82,
        "19": 106,
        "20": 108,
        "21": 95,
        "22": 77,
        "23": 64,
        "24": 60,
        "25": 68,
        "26": 53,
        "27": 57,
        "28": 51,
        "29": 55,
        "30": 55,
        "31": 41,
        "32": 43,
        "33": 20,
        "34": 34,
        "35": 29,
        "36": 18,
        "37": 18,
        "38": 13,
        "39": 16,
        "40": 13,
        "41": 7,
        "42": 10,
        "43": 5,
        "44": 4,
        "45": 2,
        "46": 1,
        "49": 1
    },
    "longest_path_cost": 20.1,
    "placement": [
        null,
        null,
        null,
        724,
        95,
        292,
        335,
        463,
        84,
        22,
        588,
        509,
        703,
        180,
        409,
        488,
        707,
        301,
        644,
        null,
        169,
        770,
        30,
        243,
        null,
        672,
        null,
        null,
        null,
        null,
        null,
        null,
        572,
        580,
        390,
        140,
        62,
        16,
        12,
        14,
        80,
        194,
        498,
        681,
        445,
        161,
        107,
        44,
        13,
        548,
        729,
        391,
        239,
        324,
        311,
        122,
        727,
        null,
        null,
        null,
        null,
        null,
        null,
        676,
        202,
        163,
        47,
        34,
        56,
        141,
        624,
        496,
        339,
        505,
        221,
        136,
        63,
        449,
        666,
        503,
        626,
        467,
        421,
        177,
        112,
        581,
        125,
        null,
        null,
        563,
        null,
        null,
        null,
        473,
        97,
        219,
        105,
        199,
        579,
        null,
        null,
        null,
        157,
        596,
        276,
        456,
        356,
        470,
        314,
        111,
        432,
        355,
        175,
        523,
        251,
        632,
        41,
        257,
        296,
        null,
        null,
        null,
        null,
        null,
        248,
        117,
        508,
        264,
        null,
        null,
        null,
        null,
        465,
        357,
        39,
        160,
        758,
        594,
        621,
        328,
        749,
        438,
        460,
        155,
        541,
        90,
        494,
        171,
        null,
        null,
        null,
        null,
        null,
        710,
        303,
        null,
        null,
        null,
        null,
        null,
        489,
        45,
        300,
        245,
        511,
        645,
        736,
        133,
        267,
        277,
        208,
        722,
        440,
        647,
        218,
        142,
        32,
        139,
        null,
        null,
        null,
        null,
        null,
        null,
        211,
        null,
        null,
        11,
        15,
        778,
        293,
        634,
        583,
        371,
        716,
        439,
        254,
        750,
        186,
        184,
        591,
        539,
        628,
        230,
        74,
        172,
        17,
        137,
        669,
        37,
        135,
        741,
        781,
        185,
        null,
        72,
        585,
        40,
        363,
        60,
        393,
        427,
        623,
        145,
        238,
        384,
        751,
        190,
        402,
        188,
        349,
        206,
        654,
        31,
        103,
        249,
        535,
        450,
        744,
        544,
        261,
        128,
        75,
        340,
        147,
        606,
        603,
        712,
        408,
        525,
        687,
        433,
        702,
        360,
        533,
        279,
        561,
        453,
        454,
        207,
        312,
        281,
        655,
        93,
        305,
        725,
        67,
        715,
        437,
        3,
        265,
        18,
        471,
        507,
        319,
        66,
        260,
        685,
        377,
        294,
        726,
        443,
        769,
        705,
        189,
        313,
        250,
        259,
        156,
        365,
        478,
        344,
        785,
        446,
        96,
        403,
        383,
        65,
        466,
        182,
        656,
        554,
        476,
        82,
        740,
        714,
        495,
        566,
        397,
        336,
        756,
        176,
        616,
        625,
        622,
        348,
        164,
        120,
        195,
        25,
        482,
        345,
        232,
        285,
        291,
        613,
        500,
        684,
        587,
        659,
        593,
        424,
        94,
        89,
        113,
        442,
        468,
        151,
        577,
        216,
        506,
        420,
        306,
        258,
        170,
        109,
        102,
        680,
        414,
        530,
        413,
        601,
        602,
        528,
        298,
        201,
        217,
        233,
        91,
        543,
        436,
        752,
        589,
        270,
        713,
        590,
        462,
        627,
        178,
        660,
        599,
        200,
        168,
        126,
        76,
        55,
        444,
        406,
        412,
        407,
        732,
        553,
        283,
        337,
        209,
        643,
        387,
        123,
        515,
        441,
        124,
        268,
        307,
        204,
        153,
        688,
        405,
        410,
        364,
        315,
        193,
        118,
        64,
        58,
        49,
        497,
        609,
        698,
        746,
        745,
        485,
        550,
        342,
        284,
        695,
        475,
        573,
        179,
        704,
        618,
        278,
        159,
        331,
        767,
        711,
        540,
        380,
        225,
        165,
        130,
        70,
        53,
        50,
        27,
        255,
        760,
        574,
        642,
        762,
        612,
        569,
        394,
        316,
        723,
        338,
        582,
        614,
        181,
        570,
        416,
        36,
        322,
        362,
        592,
        256,
        198,
        144,
        121,
        73,
        59,
        35,
        19,
        8,
        26,
        484,
        491,
        522,
        674,
        673,
        776,
        514,
        481,
        690,
        88,
        352,
        754,
        693,
        203,
        404,
        269,
        559,
        332,
        388,
        350,
        290,
        297,
        150,
        138,
        79,
        51,
        48,
        33,
        607,
        395,
        376,
        455,
        524,
        682,
        527,
        650,
        516,
        658,
        425,
        487,
        369,
        334,
        719,
        99,
        354,
        565,
        361,
        309,
        526,
        560,
        568,
        197,
        143,
        129,
        81,
        57,
        46,
        532,
        423,
        353,
        399,
        457,
        537,
        641,
        662,
        730,
        447,
        426,
        329,
        779,
        699,
        381,
        652,
        98,
        701,
        464,
        272,
        700,
        558,
        564,
        739,
        210,
        191,
        110,
        106,
        61,
        273,
        401,
        288,
        358,
        400,
        418,
        600,
        668,
        608,
        513,
        461,
        415,
        343,
        231,
        610,
        375,
        448,
        665,
        501,
        429,
        576,
        386,
        373,
        631,
        452,
        222,
        173,
        116,
        77,
        378,
        551,
        271,
        302,
        310,
        359,
        474,
        521,
        633,
        555,
        617,
        346,
        763,
        611,
        0,
        149,
        639,
        83,
        428,
        323,
        333,
        132,
        706,
        274,
        236,
        520,
        244,
        183,
        127,
        562,
        398,
        241,
        262,
        299,
        351,
        372,
        486,
        512,
        604,
        692,
        697,
        479,
        347,
        280,
        784,
        640,
        154,
        434,
        728,
        366,
        717,
        417,
        630,
        458,
        469,
        472,
        212,
        192,
        24,
        374,
        146,
        227,
        266,
        286,
        321,
        708,
        663,
        720,
        629,
        709,
        764,
        761,
        694,
        651,
        85,
        158,
        477,
        295,
        367,
        252,
        229,
        247,
        679,
        327,
        534,
        411,
        196,
        419,
        493,
        43,
        187,
        220,
        242,
        782,
        499,
        167,
        396,
        598,
        678,
        771,
        766,
        718,
        759,
        174,
        422,
        492,
        430,
        382,
        529,
        737,
        686,
        282,
        753,
        518,
        638,
        567,
        320,
        451,
        38,
        134,
        215,
        237,
        341,
        318,
        115,
        226,
        389,
        683,
        667,
        772,
        734,
        648,
        87,
        92,
        552,
        435,
        385,
        542,
        742,
        637,
        304,
        536,
        747,
        392,
        289,
        671,
        28,
        5,
        42,
        78,
        538,
        214,
        108,
        71,
        148,
        275,
        586,
        502,
        657,
        755,
        733,
        653,
        480,
        584,
        531,
        773,
        459,
        597,
        777,
        308,
        483,
        546,
        370,
        504,
        114,
        287,
        2,
        10,
        431,
        166,
        131,
        68,
        6,
        100,
        119,
        325,
        549,
        775,
        689,
        748,
        675,
        635,
        547,
        783,
        213,
        228,
        721,
        780,
        246,
        490,
        253,
        379,
        519,
        646,
        774,
        21,
        636,
        205,
        104,
        69,
        52,
        4,
        9,
        54,
        162,
        224,
        326,
        556,
        664,
        661,
        743,
        620,
        317,
        223,
        86,
        578,
        571,
        510,
        235,
        152,
        768,
        575,
        757,
        null,
        605,
        738,
        263,
        240,
        368,
        595,
        20,
        615,
        691,
        23,
        677,
        765,
        731,
        557,
        649,
        330,
        234,
        670,
        1,
        7,
        735,
        29,
        619,
        517,
        696,
        101,
        545,
        null
    ],
    "n2c": [
        593,
        831,
        755,
        269,
        790,
        726,
        761,
        832,
        462,
        791,
        756,
        187,
        38,
        48,
        39,
        188,
        37,
        206,
        271,
        461,
        819,
        784,
        9,
        822,
        637,
        319,
        463,
        433,
        725,
        834,
        22,
        233,
        176,
        491,
        67,
        460,
        450,
        209,
        697,
        134,
        217,
        116,
        727,
        668,
        47,
        161,
        520,
        66,
        490,
        404,
        432,
        489,
        789,
        431,
        792,
        375,
        68,
        519,
        403,
        459,
        219,
        549,
        36,
        76,
        402,
        297,
        275,
        266,
        760,
        788,
        430,
        732,
        215,
        458,
        204,
        242,
        374,
        578,
        728,
        488,
        40,
        518,
        303,
        596,
        8,
        653,
        803,
        711,
        473,
        333,
        145,
        358,
        712,
        263,
        332,
        4,
        294,
        94,
        537,
        507,
        762,
        838,
        346,
        234,
        787,
        96,
        548,
        46,
        731,
        345,
        547,
        109,
        84,
        334,
        753,
        703,
        577,
        125,
        401,
        763,
        317,
        457,
        55,
        387,
        390,
        86,
        373,
        607,
        241,
        517,
        429,
        759,
        600,
        167,
        698,
        210,
        75,
        207,
        487,
        177,
        35,
        69,
        175,
        516,
        456,
        223,
        639,
        244,
        733,
        594,
        486,
        337,
        808,
        394,
        625,
        143,
        288,
        102,
        654,
        421,
        135,
        45,
        793,
        65,
        316,
        428,
        758,
        674,
        372,
        20,
        344,
        147,
        205,
        576,
        682,
        112,
        311,
        83,
        368,
        417,
        13,
        447,
        299,
        606,
        199,
        213,
        198,
        669,
        229,
        284,
        227,
        546,
        636,
        400,
        41,
        318,
        665,
        515,
        455,
        97,
        371,
        355,
        64,
        477,
        393,
        786,
        231,
        259,
        170,
        384,
        545,
        184,
        635,
        773,
        730,
        699,
        339,
        356,
        174,
        95,
        670,
        74,
        575,
        802,
        794,
        427,
        704,
        640,
        774,
        659,
        203,
        563,
        322,
        357,
        829,
        807,
        603,
        700,
        224,
        52,
        816,
        610,
        671,
        23,
        605,
        163,
        777,
        660,
        124,
        235,
        286,
        114,
        658,
        779,
        196,
        434,
        454,
        117,
        343,
        287,
        276,
        240,
        611,
        815,
        127,
        270,
        641,
        168,
        391,
        479,
        363,
        581,
        540,
        550,
        602,
        734,
        104,
        169,
        420,
        255,
        622,
        261,
        690,
        382,
        413,
        323,
        642,
        754,
        552,
        723,
        484,
        324,
        5,
        190,
        279,
        656,
        118,
        485,
        354,
        612,
        162,
        17,
        582,
        154,
        719,
        264,
        342,
        392,
        748,
        511,
        583,
        54,
        260,
        285,
        108,
        399,
        442,
        801,
        702,
        274,
        695,
        643,
        451,
        598,
        53,
        764,
        795,
        662,
        139,
        532,
        828,
        422,
        481,
        599,
        505,
        6,
        309,
        383,
        444,
        72,
        243,
        701,
        412,
        562,
        291,
        321,
        590,
        621,
        315,
        230,
        483,
        613,
        474,
        523,
        508,
        111,
        106,
        133,
        553,
        584,
        253,
        510,
        452,
        218,
        398,
        289,
        628,
        657,
        817,
        504,
        751,
        193,
        614,
        572,
        638,
        565,
        494,
        278,
        579,
        780,
        426,
        535,
        686,
        296,
        225,
        715,
        571,
        386,
        482,
        705,
        34,
        51,
        722,
        220,
        441,
        493,
        675,
        308,
        609,
        524,
        554,
        551,
        228,
        295,
        478,
        396,
        377,
        379,
        248,
        14,
        397,
        664,
        378,
        350,
        348,
        561,
        449,
        630,
        555,
        666,
        341,
        82,
        683,
        522,
        331,
        502,
        531,
        221,
        597,
        569,
        685,
        757,
        110,
        251,
        626,
        714,
        360,
        268,
        141,
        195,
        172,
        389,
        335,
        281,
        376,
        44,
        293,
        530,
        566,
        77,
        237,
        696,
        574,
        257,
        258,
        495,
        105,
        525,
        632,
        745,
        142,
        560,
        366,
        7,
        539,
        132,
        298,
        81,
        336,
        633,
        107,
        272,
        634,
        93,
        585,
        415,
        302,
        655,
        290,
        620,
        741,
        471,
        320,
        749,
        464,
        410,
        615,
        503,
        15,
        160,
        778,
        465,
        684,
        667,
        146,
        306,
        71,
        405,
        42,
        673,
        326,
        568,
        736,
        79,
        752,
        73,
        340,
        273,
        126,
        11,
        806,
        164,
        616,
        559,
        470,
        388,
        500,
        836,
        692,
        781,
        604,
        586,
        466,
        113,
        496,
        249,
        512,
        498,
        353,
        687,
        349,
        743,
        521,
        254,
        663,
        236,
        720,
        526,
        729,
        201,
        425,
        144,
        716,
        359,
        239,
        839,
        750,
        771,
        49,
        765,
        411,
        580,
        713,
        381,
        301,
        588,
        796,
        826,
        542,
        480,
        513,
        256,
        608,
        89,
        543,
        509,
        307,
        694,
        514,
        440,
        448,
        805,
        32,
        416,
        436,
        810,
        570,
        338,
        804,
        98,
        33,
        85,
        445,
        192,
        742,
        216,
        735,
        328,
        10,
        362,
        365,
        200,
        453,
        330,
        137,
        818,
        103,
        746,
        676,
        370,
        556,
        351,
        352,
        246,
        617,
        813,
        245,
        492,
        558,
        406,
        564,
        592,
        439,
        325,
        446,
        820,
        312,
        589,
        419,
        835,
        800,
        138,
        314,
        222,
        70,
        313,
        80,
        367,
        202,
        647,
        631,
        573,
        115,
        587,
        191,
        770,
        785,
        718,
        693,
        595,
        624,
        527,
        437,
        385,
        18,
        165,
        782,
        173,
        710,
        827,
        499,
        652,
        536,
        740,
        232,
        262,
        300,
        737,
        501,
        329,
        369,
        798,
        528,
        645,
        797,
        567,
        78,
        707,
        557,
        208,
        830,
        724,
        25,
        468,
        467,
        769,
        63,
        823,
        677,
        661,
        347,
        43,
        497,
        706,
        327,
        277,
        689,
        250,
        395,
        767,
        472,
        821,
        618,
        476,
        651,
        414,
        837,
        619,
        407,
        534,
        541,
        538,
        252,
        12,
        418,
        283,
        601,
        16,
        644,
        648,
        153,
        424,
        247,
        364,
        305,
        267,
        194,
        629,
        680,
        506,
        646,
        775,
        171,
        443,
        3,
        265,
        280,
        56,
        627,
        50,
        529,
        825,
        380,
        739,
        709,
        833,
        166,
        688,
        814,
        544,
        304,
        211,
        717,
        799,
        238,
        409,
        408,
        721,
        768,
        140,
        197,
        226,
        361,
        691,
        475,
        738,
        310,
        811,
        136,
        681,
        435,
        650,
        438,
        591,
        649,
        824,
        679,
        423,
        809,
        282,
        21,
        678,
        708,
        744,
        783,
        766,
        469,
        747,
        189,
        533,
        776,
        212,
        672,
        772,
        623,
        292
    ]
}