{
    "exec_id": 71,
    "dot_name": "apex4_k4",
    "dot_path": "/home/jeronimo/GIT/PeR/benchmarks/fpga/bench_test/apex4_k4.dot",
    "placer": "yoto",
    "tries": 9722,
    "swaps": 1017,
    "edges_algorithm": "DEPTH_FIRST_WITH_PRIORITY",
    "total_cost": 36420.1,
    "histogram": {
        "1": 306,
        "2": 82,
        "3": 76,
        "4": 64,
        "5": 66,
        "6": 48,
        "7": 67,
        "8": 53,
        "9": 44,
        "10": 64,
        "11": 60,
        "12": 72,
        "13": 61,
        "14": 54,
        "15": 50,
        "16": 52,
        "17": 58,
        "18": 65,
        "19": 70,
        "20": 64,
        "21": 49,
        "22": 42,
        "23": 66,
        "24": 71,
        "25": 53,
        "26": 51,
        "27": 33,
        "28": 42,
        "29": 42,
        "30": 32,
        "31": 41,
        "32": 23,
        "33": 22,
        "34": 20,
        "35": 23,
        "36": 17,
        "37": 18,
        "38": 16,
        "39": 24,
        "40": 15,
        "41": 14,
        "42": 8,
        "43": 13,
        "44": 10,
        "45": 9,
        "46": 8,
        "47": 10,
        "48": 5,
        "49": 8,
        "50": 6,
        "51": 9,
        "52": 3,
        "53": 2,
        "54": 3,
        "55": 2,
        "56": 1,
        "57": 4,
        "58": 3,
        "59": 1,
        "60": 3,
        "61": 2,
        "64": 1,
        "65": 2
    },
    "longest_path_cost": 75.1,
    "placement": [
        null,
        null,
        813,
        1018,
        823,
        133,
        83,
        775,
        445,
        372,
        394,
        139,
        328,
        462,
        44,
        301,
        17,
        789,
        336,
        124,
        330,
        877,
        595,
        106,
        1007,
        1015,
        534,
        380,
        992,
        460,
        646,
        972,
        841,
        352,
        798,
        5,
        160,
        555,
        142,
        null,
        null,
        null,
        null,
        null,
        null,
        null,
        null,
        null,
        null,
        null,
        null,
        null,
        null,
        null,
        null,
        53,
        43,
        648,
        null,
        null,
        null,
        null,
        null,
        null,
        null,
        null,
        null,
        null,
        null,
        null,
        null,
        null,
        null,
        null,
        null,
        null,
        null,
        null,
        null,
        71,
        632,
        null,
        null,
        null,
        null,
        null,
        null,
        null,
        null,
        null,
        null,
        null,
        null,
        null,
        null,
        675,
        222,
        null,
        null,
        null,
        null,
        null,
        null,
        null,
        null,
        null,
        null,
        null,
        null,
        null,
        null,
        null,
        null,
        null,
        null,
        null,
        null,
        881,
        null,
        62,
        920,
        null,
        null,
        null,
        null,
        null,
        null,
        null,
        null,
        null,
        null,
        null,
        null,
        null,
        null,
        null,
        776,
        null,
        null,
        null,
        null,
        null,
        null,
        null,
        null,
        null,
        null,
        null,
        null,
        null,
        null,
        null,
        null,
        null,
        null,
        null,
        null,
        698,
        135,
        961,
        319,
        null,
        null,
        null,
        null,
        null,
        null,
        null,
        null,
        null,
        null,
        null,
        null,
        null,
        null,
        null,
        null,
        null,
        null,
        null,
        null,
        null,
        null,
        null,
        null,
        null,
        null,
        null,
        null,
        null,
        null,
        null,
        null,
        null,
        null,
        null,
        null,
        307,
        92,
        59,
        677,
        null,
        null,
        null,
        null,
        null,
        null,
        null,
        null,
        null,
        null,
        null,
        null,
        null,
        null,
        null,
        null,
        null,
        null,
        null,
        null,
        null,
        null,
        null,
        null,
        null,
        null,
        null,
        null,
        null,
        null,
        null,
        null,
        null,
        null,
        176,
        178,
        165,
        27,
        908,
        957,
        null,
        null,
        null,
        null,
        null,
        null,
        null,
        null,
        null,
        null,
        null,
        null,
        null,
        null,
        null,
        null,
        null,
        null,
        null,
        null,
        null,
        null,
        null,
        null,
        null,
        null,
        null,
        null,
        null,
        null,
        null,
        null,
        null,
        273,
        74,
        52,
        900,
        397,
        842,
        633,
        null,
        null,
        null,
        null,
        null,
        null,
        null,
        null,
        null,
        null,
        null,
        null,
        null,
        null,
        null,
        null,
        null,
        null,
        null,
        null,
        null,
        null,
        null,
        null,
        null,
        null,
        null,
        null,
        null,
        null,
        null,
        10,
        902,
        500,
        818,
        916,
        905,
        428,
        127,
        982,
        null,
        null,
        null,
        null,
        null,
        null,
        null,
        null,
        null,
        null,
        null,
        null,
        null,
        null,
        null,
        null,
        null,
        null,
        null,
        null,
        null,
        null,
        null,
        null,
        null,
        null,
        null,
        null,
        null,
        null,
        54,
        11,
        32,
        48,
        616,
        270,
        722,
        68,
        757,
        455,
        null,
        null,
        null,
        null,
        null,
        null,
        null,
        null,
        null,
        null,
        null,
        null,
        null,
        null,
        null,
        null,
        null,
        null,
        null,
        null,
        null,
        null,
        null,
        null,
        null,
        null,
        null,
        null,
        null,
        null,
        131,
        75,
        796,
        1005,
        300,
        811,
        996,
        651,
        249,
        682,
        null,
        null,
        null,
        null,
        null,
        null,
        null,
        null,
        null,
        null,
        null,
        null,
        null,
        null,
        null,
        null,
        null,
        null,
        null,
        null,
        965,
        909,
        null,
        null,
        null,
        null,
        null,
        null,
        459,
        149,
        959,
        50,
        639,
        4,
        973,
        56,
        531,
        215,
        205,
        498,
        null,
        null,
        null,
        null,
        null,
        null,
        null,
        null,
        null,
        null,
        null,
        null,
        null,
        null,
        null,
        null,
        null,
        null,
        764,
        986,
        294,
        57,
        null,
        null,
        null,
        null,
        null,
        null,
        342,
        101,
        772,
        245,
        82,
        692,
        599,
        733,
        285,
        79,
        171,
        566,
        null,
        null,
        null,
        null,
        null,
        null,
        null,
        null,
        null,
        null,
        null,
        null,
        null,
        null,
        null,
        null,
        null,
        null,
        770,
        295,
        99,
        347,
        86,
        466,
        null,
        null,
        260,
        708,
        644,
        39,
        620,
        252,
        808,
        911,
        559,
        345,
        81,
        25,
        64,
        164,
        null,
        null,
        null,
        null,
        null,
        null,
        null,
        null,
        null,
        null,
        null,
        null,
        null,
        null,
        null,
        null,
        null,
        638,
        415,
        981,
        755,
        13,
        181,
        398,
        null,
        717,
        296,
        875,
        653,
        38,
        598,
        745,
        374,
        589,
        477,
        60,
        1022,
        520,
        22,
        210,
        null,
        null,
        null,
        null,
        null,
        null,
        null,
        null,
        null,
        null,
        null,
        null,
        null,
        null,
        null,
        null,
        360,
        1011,
        414,
        896,
        386,
        194,
        157,
        223,
        null,
        719,
        128,
        771,
        593,
        100,
        238,
        754,
        530,
        184,
        494,
        1024,
        1025,
        526,
        540,
        828,
        null,
        null,
        null,
        null,
        null,
        null,
        null,
        null,
        null,
        null,
        null,
        null,
        null,
        null,
        null,
        null,
        264,
        389,
        543,
        490,
        172,
        504,
        895,
        107,
        412,
        734,
        63,
        652,
        313,
        558,
        904,
        759,
        159,
        6,
        503,
        405,
        422,
        419,
        116,
        604,
        null,
        null,
        null,
        null,
        null,
        null,
        null,
        null,
        null,
        null,
        null,
        null,
        null,
        1017,
        66,
        513,
        463,
        269,
        637,
        586,
        24,
        263,
        335,
        987,
        329,
        812,
        21,
        538,
        949,
        582,
        743,
        239,
        166,
        847,
        786,
        468,
        426,
        711,
        690,
        489,
        null,
        null,
        null,
        null,
        null,
        null,
        null,
        null,
        null,
        null,
        null,
        null,
        null,
        793,
        72,
        631,
        253,
        143,
        359,
        237,
        574,
        603,
        153,
        472,
        257,
        456,
        702,
        339,
        596,
        587,
        874,
        123,
        897,
        862,
        474,
        436,
        61,
        891,
        782,
        431,
        null,
        null,
        null,
        null,
        null,
        null,
        null,
        null,
        null,
        null,
        null,
        null,
        730,
        821,
        728,
        268,
        278,
        486,
        341,
        125,
        947,
        427,
        583,
        539,
        259,
        291,
        704,
        497,
        1006,
        364,
        880,
        353,
        899,
        731,
        475,
        777,
        663,
        892,
        321,
        306,
        null,
        null,
        null,
        null,
        null,
        null,
        null,
        null,
        null,
        null,
        413,
        668,
        325,
        822,
        346,
        669,
        525,
        331,
        248,
        316,
        229,
        267,
        588,
        594,
        1013,
        748,
        493,
        990,
        233,
        550,
        989,
        521,
        529,
        191,
        186,
        809,
        683,
        741,
        478,
        51,
        null,
        null,
        null,
        null,
        null,
        null,
        null,
        null,
        null,
        null,
        418,
        878,
        528,
        806,
        470,
        471,
        211,
        154,
        247,
        175,
        36,
        314,
        962,
        584,
        1019,
        383,
        495,
        714,
        670,
        557,
        997,
        308,
        310,
        173,
        42,
        810,
        542,
        970,
        860,
        147,
        null,
        null,
        null,
        null,
        null,
        null,
        null,
        null,
        null,
        824,
        814,
        424,
        192,
        832,
        511,
        302,
        199,
        224,
        250,
        129,
        12,
        182,
        288,
        585,
        890,
        752,
        937,
        740,
        678,
        206,
        277,
        213,
        95,
        843,
        781,
        607,
        544,
        687,
        889,
        537,
        null,
        null,
        null,
        null,
        null,
        null,
        null,
        null,
        null,
        454,
        879,
        214,
        126,
        629,
        515,
        592,
        487,
        363,
        138,
        29,
        377,
        189,
        7,
        322,
        378,
        399,
        942,
        452,
        240,
        505,
        991,
        691,
        934,
        868,
        787,
        643,
        117,
        744,
        19,
        120,
        null,
        null,
        null,
        null,
        null,
        null,
        null,
        738,
        541,
        400,
        297,
        58,
        152,
        737,
        109,
        499,
        221,
        98,
        35,
        309,
        510,
        536,
        948,
        289,
        762,
        927,
        401,
        105,
        41,
        509,
        971,
        703,
        950,
        869,
        792,
        647,
        168,
        750,
        694,
        1010,
        null,
        null,
        null,
        null,
        null,
        null,
        null,
        136,
        73,
        751,
        388,
        348,
        523,
        727,
        944,
        255,
        327,
        801,
        8,
        315,
        350,
        517,
        392,
        815,
        773,
        621,
        40,
        535,
        953,
        564,
        975,
        481,
        320,
        485,
        179,
        918,
        685,
        888,
        713,
        324,
        null,
        null,
        null,
        null,
        null,
        null,
        null,
        417,
        333,
        326,
        453,
        121,
        524,
        458,
        28,
        26,
        334,
        805,
        600,
        590,
        367,
        518,
        122,
        506,
        512,
        969,
        323,
        382,
        956,
        572,
        758,
        479,
        351,
        492,
        712,
        919,
        710,
        693,
        686,
        234,
        null,
        null,
        null,
        null,
        null,
        null,
        null,
        null,
        null,
        209,
        839,
        857,
        304,
        532,
        484,
        756,
        167,
        788,
        925,
        423,
        371,
        146,
        235,
        287,
        836,
        988,
        337,
        994,
        695,
        573,
        393,
        507,
        373,
        688,
        718,
        650,
        726,
        699,
        31,
        368,
        null,
        null,
        null,
        null,
        null,
        null,
        null,
        null,
        null,
        244,
        856,
        448,
        137,
        465,
        488,
        579,
        853,
        794,
        739,
        365,
        626,
        985,
        241,
        978,
        420,
        560,
        761,
        657,
        461,
        343,
        576,
        516,
        375,
        760,
        886,
        854,
        735,
        501,
        852,
        742,
        null,
        null,
        null,
        null,
        null,
        null,
        null,
        null,
        578,
        527,
        251,
        190,
        78,
        243,
        680,
        496,
        198,
        467,
        473,
        369,
        634,
        768,
        141,
        872,
        850,
        609,
        725,
        645,
        1016,
        666,
        967,
        562,
        998,
        763,
        906,
        859,
        376,
        47,
        999,
        837,
        null,
        null,
        null,
        null,
        null,
        null,
        null,
        567,
        591,
        437,
        356,
        212,
        446,
        548,
        554,
        502,
        357,
        469,
        311,
        444,
        636,
        202,
        480,
        207,
        779,
        613,
        732,
        218,
        672,
        667,
        980,
        984,
        1012,
        767,
        720,
        180,
        90,
        37,
        317,
        197,
        null,
        null,
        null,
        null,
        null,
        156,
        151,
        569,
        705,
        883,
        358,
        855,
        553,
        547,
        820,
        332,
        177,
        552,
        385,
        519,
        110,
        340,
        522,
        196,
        817,
        619,
        201,
        2,
        150,
        84,
        1000,
        858,
        272,
        769,
        274,
        94,
        45,
        9,
        23,
        716,
        null,
        null,
        null,
        null,
        893,
        684,
        395,
        281,
        706,
        723,
        941,
        816,
        404,
        457,
        464,
        188,
        161,
        69,
        556,
        104,
        103,
        3,
        102,
        580,
        830,
        292,
        108,
        87,
        679,
        293,
        225,
        1014,
        696,
        701,
        921,
        228,
        65,
        33,
        707,
        785,
        null,
        null,
        null,
        null,
        476,
        575,
        396,
        664,
        622,
        381,
        993,
        825,
        861,
        546,
        849,
        491,
        200,
        162,
        34,
        349,
        355,
        441,
        185,
        565,
        612,
        618,
        434,
        187,
        662,
        290,
        208,
        907,
        1001,
        654,
        917,
        846,
        361,
        49,
        995,
        864,
        null,
        null,
        null,
        568,
        624,
        1004,
        433,
        450,
        623,
        390,
        635,
        442,
        366,
        246,
        865,
        753,
        430,
        254,
        148,
        797,
        749,
        449,
        144,
        721,
        435,
        915,
        799,
        416,
        158,
        275,
        195,
        284,
        1021,
        955,
        912,
        876,
        432,
        438,
        951,
        747,
        null,
        null,
        658,
        807,
        545,
        85,
        439,
        697,
        220,
        894,
        829,
        640,
        145,
        230,
        1009,
        802,
        943,
        283,
        163,
        140,
        746,
        0,
        115,
        709,
        611,
        983,
        795,
        617,
        216,
        114,
        111,
        280,
        873,
        952,
        887,
        425,
        409,
        676,
        885,
        551,
        232,
        1008,
        660,
        1020,
        976,
        96,
        963,
        312,
        203,
        649,
        833,
        642,
        204,
        958,
        840,
        784,
        429,
        379,
        387,
        261,
        132,
        55,
        614,
        715,
        931,
        960,
        783,
        615,
        410,
        305,
        155,
        447,
        871,
        930,
        483,
        421,
        939,
        673,
        938,
        226,
        265,
        765,
        370,
        922,
        977,
        870,
        641,
        838,
        866,
        867,
        659,
        256,
        174,
        964,
        834,
        231,
        258,
        774,
        790,
        262,
        193,
        67,
        923,
        884,
        898,
        966,
        780,
        835,
        570,
        945,
        391,
        440,
        845,
        76,
        936,
        924,
        406,
        671,
        844,
        819,
        863,
        266,
        80,
        724,
        791,
        655,
        219,
        800,
        736,
        236,
        227,
        97,
        93,
        46,
        119,
        113,
        354,
        681,
        901,
        954,
        286,
        656,
        408,
        170,
        903,
        1002,
        299,
        602,
        935,
        940,
        571,
        402,
        169,
        88,
        928,
        913,
        89,
        661,
        362,
        514,
        451,
        803,
        1023,
        729,
        674,
        561,
        130,
        804,
        627,
        242,
        134,
        91,
        77,
        30,
        15,
        118,
        183,
        338,
        933,
        831,
        700,
        344,
        217,
        298,
        533,
        549,
        276,
        605,
        689,
        625,
        628,
        630,
        303,
        979,
        826,
        827,
        851,
        608,
        14,
        null,
        70,
        282,
        384,
        946,
        766,
        508,
        1003,
        411,
        581,
        597,
        16,
        601,
        910,
        610,
        848,
        882,
        932,
        914,
        778,
        318,
        18,
        443,
        1,
        926,
        279,
        403,
        665,
        112,
        271,
        968,
        577,
        20,
        563,
        929,
        974,
        482,
        407,
        606,
        null
    ],
    "n2c": [
        1382,
        1583,
        1228,
        1262,
        434,
        35,
        634,
        903,
        979,
        1238,
        312,
        352,
        861,
        542,
        1559,
        1535,
        1571,
        16,
        1581,
        919,
        1592,
        667,
        559,
        1239,
        661,
        518,
        1016,
        238,
        1015,
        900,
        1534,
        1079,
        353,
        1278,
        1299,
        939,
        821,
        1198,
        550,
        510,
        987,
        949,
        835,
        56,
        14,
        1237,
        1494,
        1158,
        354,
        1318,
        432,
        800,
        276,
        55,
        351,
        1422,
        436,
        462,
        932,
        199,
        556,
        717,
        119,
        627,
        519,
        1277,
        655,
        1462,
        358,
        1258,
        1561,
        79,
        695,
        969,
        275,
        392,
        1474,
        1533,
        1133,
        478,
        1483,
        517,
        473,
        6,
        1230,
        1366,
        503,
        1268,
        1514,
        1517,
        1197,
        1532,
        198,
        1493,
        1236,
        873,
        1406,
        1492,
        938,
        501,
        590,
        470,
        1263,
        1261,
        1260,
        948,
        23,
        624,
        1267,
        935,
        1221,
        1391,
        1588,
        1496,
        1390,
        1383,
        639,
        917,
        1536,
        1495,
        920,
        1012,
        1023,
        712,
        19,
        740,
        893,
        319,
        587,
        860,
        1527,
        391,
        1421,
        5,
        1531,
        158,
        968,
        1093,
        899,
        11,
        1380,
        1143,
        38,
        698,
        1343,
        1373,
        1062,
        840,
        1339,
        430,
        1229,
        1207,
        933,
        703,
        818,
        1431,
        1206,
        583,
        1349,
        633,
        36,
        1257,
        1298,
        1379,
        520,
        237,
        673,
        1057,
        957,
        1513,
        1504,
        479,
        621,
        834,
        1453,
        820,
        235,
        1217,
        236,
        995,
        1196,
        543,
        862,
        1537,
        594,
        1303,
        795,
        1308,
        1256,
        902,
        1132,
        794,
        853,
        1461,
        582,
        1351,
        1224,
        1200,
        1137,
        857,
        1297,
        1227,
        1182,
        1409,
        1413,
        439,
        870,
        1184,
        1311,
        1050,
        560,
        817,
        1172,
        872,
        892,
        438,
        1389,
        1543,
        1188,
        1487,
        1369,
        937,
        96,
        584,
        858,
        1271,
        1440,
        1491,
        1276,
        781,
        1374,
        1456,
        1401,
        789,
        1040,
        1063,
        1490,
        700,
        591,
        672,
        909,
        1103,
        1530,
        1134,
        1090,
        472,
        1334,
        819,
        779,
        399,
        859,
        1131,
        512,
        697,
        1338,
        976,
        1452,
        705,
        1457,
        745,
        507,
        1420,
        1460,
        662,
        617,
        1441,
        1482,
        782,
        736,
        658,
        356,
        1589,
        1233,
        274,
        1235,
        1350,
        1547,
        871,
        737,
        1585,
        1392,
        1248,
        1562,
        1378,
        1352,
        477,
        1501,
        1064,
        863,
        944,
        1310,
        746,
        1266,
        1270,
        461,
        500,
        547,
        931,
        1544,
        1507,
        395,
        15,
        856,
        1553,
        1053,
        1430,
        760,
        197,
        832,
        940,
        833,
        1179,
        1408,
        629,
        822,
        980,
        780,
        1199,
        1580,
        160,
        993,
        759,
        904,
        1027,
        1000,
        773,
        1010,
        977,
        12,
        665,
        20,
        778,
        1216,
        1009,
        1017,
        663,
        18,
        1067,
        1538,
        708,
        1222,
        739,
        469,
        1110,
        1542,
        516,
        775,
        502,
        972,
        1300,
        981,
        1033,
        33,
        752,
        1497,
        1301,
        1171,
        1177,
        1211,
        699,
        577,
        1317,
        1519,
        898,
        750,
        1100,
        1333,
        1021,
        1080,
        1140,
        1443,
        1061,
        9,
        1073,
        553,
        1113,
        1157,
        901,
        905,
        1418,
        27,
        1290,
        1028,
        826,
        1563,
        1219,
        581,
        1419,
        971,
        618,
        1330,
        1471,
        983,
        1071,
        10,
        1247,
        1287,
        278,
        544,
        906,
        930,
        947,
        1512,
        1586,
        1253,
        636,
        1477,
        1597,
        1503,
        1397,
        1429,
        1568,
        625,
        771,
        579,
        539,
        1348,
        1008,
        811,
        638,
        1105,
        1436,
        637,
        1060,
        852,
        1396,
        677,
        742,
        318,
        1417,
        1337,
        720,
        1357,
        1327,
        1307,
        1345,
        716,
        1170,
        1358,
        1367,
        1472,
        1302,
        1332,
        1582,
        1180,
        8,
        1173,
        1432,
        1092,
        1342,
        1328,
        1521,
        908,
        1011,
        890,
        360,
        706,
        1254,
        1014,
        429,
        29,
        1109,
        13,
        657,
        1255,
        1094,
        504,
        1138,
        676,
        1178,
        815,
        816,
        704,
        1139,
        715,
        755,
        1285,
        555,
        799,
        1032,
        1183,
        992,
        1596,
        1435,
        1055,
        994,
        738,
        897,
        1095,
        680,
        620,
        1296,
        1034,
        787,
        595,
        827,
        1136,
        748,
        440,
        936,
        314,
        1118,
        1176,
        635,
        622,
        910,
        1024,
        1072,
        1566,
        950,
        941,
        855,
        1025,
        656,
        1520,
        895,
        1112,
        982,
        1022,
        1220,
        558,
        792,
        1223,
        973,
        1013,
        777,
        598,
        1130,
        813,
        793,
        593,
        437,
        1054,
        1545,
        26,
        988,
        942,
        880,
        668,
        744,
        599,
        929,
        837,
        619,
        877,
        1365,
        1294,
        1214,
        1174,
        1546,
        790,
        1400,
        1218,
        1213,
        1175,
        37,
        1259,
        830,
        630,
        515,
        1106,
        1526,
        1152,
        1593,
        990,
        1304,
        480,
        1168,
        1324,
        1208,
        1469,
        1511,
        1030,
        1070,
        701,
        1286,
        1111,
        1591,
        1129,
        1096,
        1264,
        1569,
        670,
        743,
        824,
        864,
        660,
        710,
        783,
        554,
        1020,
        1169,
        896,
        589,
        784,
        22,
        709,
        1570,
        551,
        475,
        1019,
        1572,
        1508,
        702,
        640,
        1548,
        1598,
        876,
        1558,
        1146,
        1574,
        1385,
        1305,
        1186,
        1423,
        1428,
        355,
        1388,
        1306,
        1226,
        511,
        986,
        1289,
        1329,
        1325,
        1550,
        1101,
        1529,
        1551,
        894,
        1552,
        696,
        80,
        280,
        1141,
        1331,
        1181,
        659,
        538,
        433,
        1372,
        1447,
        1412,
        916,
        509,
        1148,
        30,
        956,
        57,
        1410,
        1076,
        398,
        628,
        549,
        1314,
        1486,
        1502,
        1108,
        1363,
        1451,
        1403,
        1518,
        1309,
        757,
        1288,
        1587,
        1150,
        1190,
        772,
        776,
        829,
        1478,
        1189,
        1438,
        1525,
        95,
        1398,
        200,
        869,
        1269,
        1135,
        1498,
        400,
        797,
        1246,
        997,
        1039,
        878,
        1074,
        1549,
        679,
        912,
        474,
        1038,
        959,
        1069,
        1273,
        1368,
        157,
        1078,
        1541,
        1274,
        707,
        952,
        747,
        1209,
        1249,
        1279,
        508,
        1384,
        1037,
        678,
        1035,
        999,
        828,
        1424,
        1240,
        546,
        1075,
        586,
        1195,
        1344,
        357,
        1250,
        1484,
        1147,
        1077,
        974,
        735,
        1524,
        733,
        754,
        1187,
        476,
        626,
        1117,
        1489,
        934,
        928,
        1099,
        868,
        798,
        1120,
        671,
        918,
        552,
        1381,
        1360,
        786,
        1341,
        958,
        970,
        866,
        1336,
        592,
        541,
        1056,
        359,
        1031,
        632,
        1114,
        1107,
        945,
        1154,
        459,
        1442,
        1565,
        1194,
        1142,
        1234,
        499,
        588,
        471,
        985,
        1458,
        7,
        136,
        756,
        1579,
        1185,
        1467,
        875,
        719,
        1427,
        1416,
        1280,
        675,
        915,
        1058,
        17,
        1459,
        1485,
        955,
        694,
        1098,
        1387,
        393,
        1340,
        34,
        1347,
        1488,
        978,
        1376,
        1522,
        1528,
        1018,
        814,
        1364,
        513,
        796,
        836,
        396,
        666,
        2,
        851,
        984,
        1252,
        1225,
        315,
        1480,
        1215,
        734,
        774,
        4,
        850,
        1292,
        1555,
        1556,
        600,
        1371,
        1265,
        1540,
        854,
        1411,
        1455,
        1468,
        1065,
        1160,
        1448,
        1051,
        1415,
        32,
        279,
        874,
        1479,
        1473,
        1316,
        674,
        1575,
        1295,
        1145,
        1557,
        1119,
        1097,
        1116,
        1212,
        1091,
        1052,
        1232,
        1156,
        839,
        1293,
        714,
        1481,
        1320,
        1335,
        1449,
        1450,
        914,
        954,
        1446,
        1433,
        1144,
        1393,
        711,
        548,
        1356,
        21,
        812,
        891,
        751,
        117,
        1576,
        1210,
        1464,
        1399,
        1115,
        1395,
        998,
        879,
        865,
        718,
        758,
        1245,
        1370,
        623,
        580,
        713,
        1465,
        753,
        277,
        1499,
        313,
        1505,
        631,
        317,
        1155,
        1312,
        239,
        422,
        1573,
        514,
        1355,
        1516,
        1578,
        1346,
        316,
        1315,
        996,
        1036,
        120,
        1275,
        1444,
        1463,
        1476,
        1059,
        1584,
        946,
        1515,
        1594,
        1434,
        1425,
        1577,
        1539,
        913,
        1509,
        1475,
        867,
        1439,
        1437,
        1510,
        1251,
        907,
        1377,
        975,
        1470,
        1564,
        741,
        943,
        669,
        953,
        1359,
        1394,
        989,
        1500,
        1354,
        1029,
        240,
        1414,
        431,
        1426,
        159,
        823,
        1407,
        1454,
        421,
        1466,
        1151,
        1590,
        1026,
        838,
        951,
        31,
        435,
        1595,
        991,
        1405,
        1445,
        1104,
        1554,
        1191,
        540,
        320,
        1386,
        1192,
        1102,
        460,
        664,
        1066,
        791,
        788,
        911,
        28,
        1291,
        1068,
        1319,
        397,
        831,
        1153,
        1159,
        1231,
        1313,
        1506,
        1567,
        1326,
        394,
        749,
        24,
        1402,
        1375,
        960,
        578,
        1193,
        785,
        1272,
        25,
        1149,
        654,
        3,
        825,
        1404,
        1353,
        557,
        1523,
        596,
        597
    ]
}