{
    "exec_id": 33,
    "dot_name": "ex5p_k5",
    "dot_path": "/home/jeronimo/GIT/PeR/benchmarks/fpga/bench_test/ex5p_k5.dot",
    "placer": "yoto",
    "tries": 6003,
    "swaps": 703,
    "edges_algorithm": "DEPTH_FIRST_WITH_PRIORITY",
    "total_cost": 29646.1,
    "histogram": {
        "1": 161,
        "2": 63,
        "3": 64,
        "4": 62,
        "5": 72,
        "6": 74,
        "7": 84,
        "8": 77,
        "9": 79,
        "10": 71,
        "11": 82,
        "12": 82,
        "13": 80,
        "14": 94,
        "15": 66,
        "16": 67,
        "17": 54,
        "18": 53,
        "19": 77,
        "20": 69,
        "21": 44,
        "22": 54,
        "23": 52,
        "24": 36,
        "25": 50,
        "26": 34,
        "27": 37,
        "28": 36,
        "29": 34,
        "30": 29,
        "31": 27,
        "32": 17,
        "33": 20,
        "34": 12,
        "35": 12,
        "36": 14,
        "37": 13,
        "38": 9,
        "39": 14,
        "40": 6,
        "41": 6,
        "42": 8,
        "43": 6,
        "44": 4,
        "45": 4,
        "46": 1,
        "47": 1,
        "48": 2,
        "49": 1
    },
    "longest_path_cost": 86.1,
    "placement": [
        null,
        269,
        355,
        15,
        501,
        264,
        377,
        12,
        434,
        694,
        570,
        533,
        640,
        550,
        681,
        619,
        653,
        289,
        196,
        47,
        258,
        296,
        710,
        10,
        574,
        406,
        344,
        685,
        null,
        225,
        669,
        517,
        57,
        228,
        270,
        295,
        275,
        274,
        652,
        573,
        548,
        436,
        233,
        213,
        132,
        127,
        71,
        29,
        27,
        69,
        81,
        97,
        142,
        206,
        351,
        468,
        664,
        631,
        155,
        110,
        621,
        560,
        220,
        608,
        268,
        440,
        247,
        578,
        582,
        540,
        487,
        435,
        251,
        170,
        138,
        93,
        73,
        49,
        77,
        114,
        134,
        172,
        234,
        481,
        557,
        661,
        11,
        350,
        99,
        3,
        577,
        84,
        602,
        276,
        554,
        218,
        569,
        697,
        535,
        486,
        568,
        403,
        248,
        190,
        158,
        87,
        72,
        124,
        140,
        204,
        259,
        402,
        478,
        551,
        659,
        658,
        14,
        39,
        35,
        5,
        263,
        600,
        271,
        147,
        405,
        352,
        695,
        483,
        643,
        567,
        682,
        393,
        294,
        171,
        169,
        94,
        139,
        207,
        245,
        417,
        566,
        469,
        454,
        515,
        452,
        262,
        182,
        48,
        21,
        46,
        458,
        641,
        492,
        314,
        346,
        583,
        267,
        584,
        552,
        380,
        455,
        442,
        293,
        193,
        136,
        187,
        250,
        399,
        416,
        609,
        660,
        502,
        512,
        513,
        599,
        531,
        91,
        45,
        109,
        709,
        529,
        472,
        313,
        675,
        192,
        398,
        572,
        514,
        667,
        633,
        636,
        368,
        214,
        175,
        241,
        374,
        646,
        407,
        516,
        696,
        589,
        630,
        647,
        302,
        528,
        465,
        389,
        390,
        561,
        28,
        191,
        376,
        154,
        693,
        396,
        278,
        663,
        382,
        451,
        656,
        530,
        401,
        310,
        364,
        490,
        482,
        473,
        686,
        349,
        532,
        345,
        590,
        356,
        457,
        702,
        387,
        494,
        107,
        662,
        505,
        63,
        617,
        428,
        135,
        265,
        547,
        378,
        359,
        654,
        527,
        620,
        445,
        397,
        485,
        372,
        395,
        592,
        581,
        606,
        427,
        470,
        323,
        180,
        340,
        384,
        650,
        365,
        255,
        339,
        562,
        642,
        424,
        130,
        414,
        304,
        325,
        558,
        676,
        522,
        616,
        443,
        379,
        471,
        360,
        520,
        254,
        252,
        536,
        632,
        521,
        319,
        290,
        329,
        362,
        118,
        249,
        493,
        665,
        326,
        475,
        456,
        74,
        657,
        168,
        369,
        239,
        673,
        409,
        611,
        441,
        361,
        593,
        571,
        563,
        704,
        668,
        534,
        423,
        610,
        626,
        282,
        343,
        90,
        209,
        404,
        556,
        575,
        102,
        243,
        386,
        59,
        215,
        152,
        495,
        684,
        284,
        707,
        508,
        439,
        358,
        591,
        240,
        559,
        698,
        219,
        413,
        419,
        666,
        701,
        179,
        137,
        208,
        332,
        629,
        625,
        86,
        237,
        320,
        373,
        277,
        506,
        224,
        160,
        488,
        266,
        201,
        497,
        305,
        412,
        216,
        415,
        223,
        699,
        637,
        316,
        408,
        438,
        58,
        392,
        291,
        489,
        256,
        634,
        645,
        167,
        321,
        317,
        690,
        353,
        120,
        700,
        149,
        484,
        598,
        148,
        331,
        298,
        524,
        198,
        549,
        221,
        222,
        615,
        618,
        17,
        672,
        410,
        542,
        464,
        648,
        363,
        328,
        639,
        579,
        189,
        622,
        688,
        165,
        411,
        683,
        52,
        83,
        594,
        153,
        324,
        173,
        178,
        300,
        203,
        129,
        56,
        279,
        677,
        66,
        357,
        62,
        538,
        564,
        199,
        655,
        523,
        544,
        151,
        580,
        612,
        32,
        297,
        117,
        433,
        371,
        446,
        281,
        285,
        176,
        186,
        145,
        128,
        587,
        537,
        453,
        125,
        272,
        95,
        496,
        23,
        141,
        43,
        82,
        161,
        480,
        338,
        418,
        336,
        156,
        31,
        64,
        334,
        0,
        367,
        703,
        607,
        503,
        133,
        177,
        525,
        318,
        671,
        526,
        80,
        null,
        null,
        null,
        13,
        30,
        184,
        131,
        115,
        585,
        188,
        553,
        287,
        116,
        603,
        202,
        638,
        4,
        67,
        92,
        195,
        605,
        500,
        596,
        366,
        119,
        301,
        55,
        121,
        null,
        null,
        null,
        null,
        604,
        691,
        555,
        370,
        143,
        400,
        543,
        391,
        122,
        227,
        65,
        459,
        9,
        41,
        126,
        163,
        197,
        226,
        546,
        477,
        312,
        613,
        101,
        null,
        689,
        null,
        null,
        null,
        null,
        299,
        692,
        70,
        25,
        388,
        595,
        430,
        565,
        42,
        194,
        309,
        19,
        24,
        76,
        112,
        212,
        510,
        231,
        123,
        311,
        246,
        327,
        54,
        null,
        null,
        null,
        null,
        null,
        null,
        217,
        708,
        113,
        183,
        467,
        463,
        425,
        230,
        539,
        2,
        22,
        37,
        85,
        601,
        461,
        628,
        44,
        705,
        null,
        null,
        null,
        322,
        null,
        null,
        null,
        null,
        null,
        null,
        null,
        422,
        687,
        205,
        280,
        448,
        624,
        51,
        303,
        330,
        18,
        68,
        144,
        431,
        429,
        541,
        597,
        79,
        315,
        null,
        null,
        null,
        null,
        null,
        null,
        null,
        null,
        null,
        null,
        null,
        614,
        341,
        286,
        306,
        447,
        627,
        244,
        649,
        383,
        38,
        96,
        16,
        242,
        679,
        333,
        106,
        635,
        null,
        null,
        null,
        null,
        null,
        null,
        null,
        null,
        null,
        null,
        null,
        null,
        474,
        460,
        623,
        157,
        385,
        288,
        586,
        511,
        75,
        108,
        103,
        162,
        283,
        670,
        210,
        462,
        200,
        null,
        null,
        null,
        null,
        null,
        null,
        null,
        null,
        null,
        null,
        null,
        null,
        674,
        545,
        6,
        166,
        273,
        347,
        60,
        499,
        78,
        181,
        354,
        644,
        33,
        111,
        479,
        100,
        null,
        null,
        null,
        null,
        null,
        null,
        null,
        null,
        null,
        null,
        null,
        null,
        null,
        8,
        421,
        40,
        235,
        308,
        185,
        466,
        174,
        164,
        509,
        61,
        105,
        307,
        432,
        519,
        null,
        null,
        null,
        null,
        null,
        null,
        null,
        null,
        null,
        null,
        null,
        null,
        null,
        null,
        335,
        437,
        229,
        7,
        706,
        337,
        507,
        292,
        89,
        498,
        88,
        257,
        518,
        491,
        null,
        null,
        null,
        null,
        null,
        null,
        null,
        null,
        null,
        null,
        null,
        null,
        null,
        null,
        null,
        260,
        20,
        236,
        261,
        381,
        null,
        null,
        348,
        null,
        34,
        211,
        null,
        null,
        null,
        null,
        null,
        null,
        null,
        null,
        null,
        null,
        null,
        null,
        null,
        null,
        null,
        null,
        null,
        null,
        504,
        null,
        680,
        476,
        450,
        678,
        104,
        159,
        420,
        651,
        1,
        253,
        576,
        238,
        444,
        588,
        232,
        150,
        146,
        26,
        50,
        375,
        426,
        98,
        342,
        53,
        394,
        36,
        449,
        null
    ],
    "n2c": [
        477,
        821,
        588,
        89,
        505,
        119,
        697,
        756,
        724,
        533,
        23,
        86,
        7,
        492,
        116,
        3,
        648,
        404,
        617,
        561,
        783,
        148,
        589,
        464,
        562,
        553,
        830,
        48,
        209,
        47,
        493,
        474,
        445,
        707,
        791,
        118,
        838,
        590,
        646,
        117,
        726,
        534,
        558,
        466,
        595,
        177,
        149,
        19,
        147,
        77,
        831,
        614,
        420,
        836,
        572,
        515,
        430,
        32,
        377,
        330,
        701,
        734,
        435,
        240,
        475,
        531,
        433,
        506,
        618,
        49,
        552,
        46,
        106,
        76,
        301,
        674,
        563,
        78,
        703,
        624,
        488,
        50,
        467,
        421,
        91,
        591,
        355,
        105,
        763,
        761,
        322,
        176,
        507,
        75,
        135,
        462,
        647,
        51,
        834,
        88,
        710,
        543,
        327,
        676,
        817,
        735,
        652,
        237,
        675,
        178,
        59,
        708,
        564,
        581,
        79,
        496,
        501,
        447,
        294,
        513,
        389,
        516,
        529,
        568,
        107,
        460,
        535,
        45,
        456,
        429,
        272,
        495,
        44,
        482,
        80,
        243,
        164,
        350,
        74,
        136,
        108,
        465,
        52,
        525,
        619,
        455,
        829,
        123,
        394,
        391,
        828,
        442,
        332,
        423,
        212,
        58,
        473,
        669,
        104,
        818,
        362,
        468,
        677,
        536,
        732,
        417,
        698,
        384,
        303,
        134,
        73,
        133,
        81,
        425,
        731,
        193,
        453,
        483,
        426,
        349,
        262,
        704,
        146,
        582,
        494,
        729,
        454,
        165,
        498,
        414,
        103,
        210,
        184,
        163,
        559,
        508,
        18,
        537,
        398,
        438,
        682,
        365,
        503,
        428,
        109,
        610,
        53,
        137,
        351,
        323,
        680,
        792,
        565,
        43,
        192,
        331,
        369,
        579,
        95,
        344,
        62,
        400,
        401,
        371,
        361,
        29,
        538,
        530,
        33,
        755,
        586,
        567,
        827,
        42,
        82,
        727,
        784,
        356,
        824,
        305,
        341,
        194,
        649,
        328,
        643,
        138,
        570,
        66,
        102,
        295,
        166,
        72,
        286,
        822,
        285,
        267,
        381,
        764,
        20,
        110,
        782,
        785,
        145,
        120,
        5,
        244,
        364,
        156,
        64,
        1,
        34,
        122,
        461,
        699,
        37,
        36,
        93,
        359,
        215,
        431,
        611,
        451,
        320,
        678,
        335,
        452,
        639,
        500,
        671,
        17,
        291,
        379,
        760,
        162,
        132,
        35,
        21,
        446,
        396,
        550,
        427,
        514,
        203,
        615,
        274,
        367,
        640,
        736,
        728,
        560,
        222,
        569,
        541,
        182,
        153,
        625,
        374,
        386,
        485,
        290,
        357,
        385,
        600,
        261,
        424,
        275,
        298,
        571,
        411,
        292,
        616,
        395,
        352,
        651,
        476,
        753,
        472,
        758,
        470,
        268,
        263,
        638,
        835,
        321,
        26,
        230,
        154,
        700,
        789,
        228,
        87,
        54,
        125,
        388,
        705,
        2,
        232,
        434,
        339,
        247,
        283,
        310,
        293,
        410,
        223,
        266,
        512,
        478,
        191,
        304,
        524,
        449,
        254,
        358,
        195,
        832,
        211,
        6,
        246,
        281,
        159,
        786,
        217,
        645,
        264,
        670,
        329,
        235,
        554,
        206,
        207,
        528,
        378,
        131,
        837,
        255,
        214,
        252,
        185,
        167,
        526,
        221,
        111,
        101,
        324,
        124,
        25,
        197,
        375,
        307,
        406,
        418,
        368,
        345,
        273,
        370,
        168,
        139,
        471,
        346,
        819,
        725,
        608,
        317,
        271,
        585,
        833,
        259,
        242,
        621,
        556,
        620,
        737,
        448,
        8,
        71,
        41,
        754,
        376,
        338,
        65,
        309,
        161,
        280,
        825,
        251,
        450,
        641,
        612,
        839,
        815,
        218,
        144,
        459,
        142,
        160,
        300,
        233,
        150,
        532,
        667,
        593,
        681,
        584,
        408,
        205,
        730,
        583,
        55,
        141,
        260,
        282,
        181,
        226,
        666,
        299,
        814,
        540,
        112,
        709,
        469,
        83,
        225,
        127,
        392,
        253,
        99,
        70,
        363,
        380,
        224,
        766,
        152,
        296,
        236,
        333,
        463,
        366,
        762,
        702,
        510,
        4,
        171,
        481,
        811,
        239,
        360,
        759,
        337,
        733,
        566,
        673,
        172,
        173,
        187,
        143,
        198,
        31,
        765,
        738,
        284,
        289,
        278,
        440,
        397,
        484,
        487,
        249,
        204,
        180,
        220,
        175,
        229,
        11,
        316,
        98,
        287,
        458,
        436,
        587,
        69,
        622,
        407,
        527,
        441,
        696,
        539,
        245,
        40,
        399,
        13,
        113,
        158,
        499,
        94,
        523,
        325,
        84,
        276,
        342,
        61,
        208,
        269,
        313,
        437,
        557,
        140,
        129,
        100,
        96,
        10,
        312,
        186,
        39,
        24,
        326,
        823,
        90,
        67,
        413,
        443,
        257,
        68,
        155,
        157,
        497,
        672,
        457,
        826,
        200,
        231,
        340,
        256,
        311,
        422,
        555,
        511,
        623,
        393,
        174,
        121,
        592,
        92,
        502,
        521,
        509,
        258,
        480,
        63,
        169,
        318,
        308,
        444,
        542,
        637,
        402,
        279,
        241,
        403,
        15,
        250,
        60,
        415,
        668,
        613,
        354,
        319,
        642,
        594,
        353,
        201,
        57,
        288,
        189,
        382,
        653,
        190,
        373,
        504,
        412,
        12,
        151,
        270,
        128,
        706,
        383,
        196,
        202,
        409,
        644,
        265,
        820,
        38,
        16,
        248,
        439,
        219,
        302,
        115,
        114,
        170,
        85,
        238,
        216,
        56,
        297,
        347,
        188,
        315,
        30,
        679,
        486,
        405,
        306,
        695,
        183,
        277,
        432,
        816,
        650,
        813,
        14,
        130,
        419,
        334,
        27,
        227,
        609,
        416,
        545,
        387,
        522,
        551,
        213,
        9,
        126,
        199,
        97,
        343,
        372,
        390,
        348,
        234,
        479,
        314,
        596,
        757,
        336,
        580,
        179,
        22
    ]
}